fastapi_socketio/__init__.py
fastapi_socketio/socket_manager.py
fastapi_socketio-0.0.10.dist-info/LICENSE
fastapi_socketio-0.0.10.dist-info/METADATA
fastapi_socketio-0.0.10.dist-info/WHEEL
fastapi_socketio-0.0.10.dist-info/top_level.txt
fastapi_socketio-0.0.10.dist-info/RECORD
