Metadata-Version: 2.1
Name: fastapi-socketio
Version: 0.0.10
Summary: Easily integrate socket.io with your FastAPI app.
Home-page: https://github.com/pyropy/fastapi-socketio
Author: Srdjan Stankovic
Author-email: stankovic.srdjo@gmail.com
License: Apache License, Version 2.0
Project-URL: Issues, https://github.com/pyropy/fastapi-socketio/issues
Project-URL: CI, https://github.com/pyropy/fastapi-socketio/actions
Project-URL: Changelog, https://github.com/pyropy/fastapi-socketio/releases
Platform: UNKNOWN
Provides-Extra: test
